[
{"name":"Espresso","price":95,"category":"BREWS","available":true},
{"name":"Americano","price":114,"category":"BREWS","available":true},
{"name":"Cappuccino","price":133,"category":"BREWS","available":true},
{"name":"Mocha","price":152,"category":"BREWS","available":true},
{"name":"Cold Coffee","price":190,"category":"BREWS","available":true},
{"name":"Masala Chai","price":57,"category":"BREWS","available":true},
{"name":"Green Tea","price":86,"category":"BREWS","available":true},
{"name":"Ginger Lemon Honey Tea","price":116,"category":"BREWS","available":true},
{"name":"Milk Coffee","price":95,"category":"BREWS","available":true},
{"name":"Filter Coffee","price":95,"category":"BREWS","available":true},

{"name":"Sweet Lassi","price":134,"category":"LASSI","available":true},
{"name":"Masala Lassi","price":134,"category":"LASSI","available":true},
{"name":"Banana & Honey Lassi","price":153,"category":"LASSI","available":true},

{"name":"Watermelon Juice","price":153,"category":"SLOW PRESSED FRESH JUICES","available":true},
{"name":"Pineapple Juice","price":200,"category":"SLOW PRESSED FRESH JUICES","available":true},
{"name":"Orange Juice","price":210,"category":"SLOW PRESSED FRESH JUICES","available":true},

{"name":"Aerated Drinks Can","price":71,"category":"SOFT BEVERAGES","available":true},
{"name":"Schweppes Tonic Water","price":95,"category":"SOFT BEVERAGES","available":true},
{"name":"Schweppes Ginger Ale","price":95,"category":"SOFT BEVERAGES","available":true},
{"name":"Red Bull","price":200,"category":"SOFT BEVERAGES","available":true},
{"name":"Fresh Lime Soda / Water","price":95,"category":"SOFT BEVERAGES","available":true},
{"name":"Coconut Water","price":153,"category":"SOFT BEVERAGES","available":true},
{"name":"Bottle Of Water","price":29,"category":"SOFT BEVERAGES","available":true},

{"name":"Indian Breakfast","price":296,"category":"BREAKFAST THALI","available":true,"desc":"Aloo Parantha, Savoury, Sprouts, Fresh Fruit, Juice, Tea/Coffee"},
{"name":"Continental Breakfast","price":296,"category":"BREAKFAST THALI","available":true,"desc":"Fresh Fruit, Toast, Bakery, Choice of Egg, Juice, Tea/Coffee"},
{"name":"English Breakfast","price":458,"category":"BREAKFAST THALI","available":true,"desc":"Baked Beans, Egg, Bread, Chicken Sausage, Chicken Salami, Roast Potato & Mushroom"},

{"name":"Aloo Parantha","price":152,"category":"BREAKFAST ADD-ONS","available":true},
{"name":"Paneer Parantha","price":200,"category":"BREAKFAST ADD-ONS","available":true},
{"name":"Cornflakes with Milk","price":133,"category":"BREAKFAST ADD-ONS","available":true},
{"name":"Crunchy Muesli with Milk","price":162,"category":"BREAKFAST ADD-ONS","available":true},
{"name":"Baked Beans with Toast","price":210,"category":"BREAKFAST ADD-ONS","available":true},
{"name":"Homemade Toast (Butter & Jam)","price":76,"category":"BREAKFAST ADD-ONS","available":true},

{"name":"Fried Egg","price":162,"category":"EGGS","available":true},
{"name":"Plain Omelette","price":162,"category":"EGGS","available":true},
{"name":"Masala Omelette","price":171,"category":"EGGS","available":true},
{"name":"Cheese Omelette","price":181,"category":"EGGS","available":true},
{"name":"Scrambled Egg","price":162,"category":"EGGS","available":true},
{"name":"Boiled Egg","price":162,"category":"EGGS","available":true},

{"name":"Butter Croissant","price":76,"category":"ALL DAY FRESHLY BAKED","available":true},
{"name":"Cheese Croissant","price":86,"category":"ALL DAY FRESHLY BAKED","available":true},
{"name":"Chocolate Croissant","price":95,"category":"ALL DAY FRESHLY BAKED","available":true},
{"name":"Cinnamon Danish Pastry","price":124,"category":"ALL DAY FRESHLY BAKED","available":true},
{"name":"Vegetable Puff","price":105,"category":"ALL DAY FRESHLY BAKED","available":true},
{"name":"Chicken Puff","price":124,"category":"ALL DAY FRESHLY BAKED","available":true},

{"name":"Coleslaw Sandwich","price":219,"category":"SANDWICHES & BURGERS","available":true},
{"name":"Tomato, Cucumber & Cheese Sandwich","price":229,"category":"SANDWICHES & BURGERS","available":true},
{"name":"Chicken Ham & Cheese Sandwich","price":324,"category":"SANDWICHES & BURGERS","available":true},
{"name":"Focaccia Paneer Tikka Sandwich","price":324,"category":"SANDWICHES & BURGERS","available":true},
{"name":"Focaccia Chicken Tikka Sandwich","price":343,"category":"SANDWICHES & BURGERS","available":true},
{"name":"Vegetable Burger","price":229,"category":"SANDWICHES & BURGERS","available":true},
{"name":"Chicken Burger","price":248,"category":"SANDWICHES & BURGERS","available":true},

{"name":"French Fries","price":171,"category":"STARTERS","available":true},
{"name":"Mexican Potato Wedges","price":191,"category":"STARTERS","available":true},
{"name":"Masala Peanut","price":159,"category":"STARTERS","available":true},
{"name":"Masala Papad","price":119,"category":"STARTERS","available":true},
{"name":"Roasted Papad","price":69,"category":"STARTERS","available":true},
{"name":"Vegetable Cutlet","price":191,"category":"STARTERS","available":true},
{"name":"Crispy Chicken Salsa","price":314,"category":"STARTERS","available":true},
{"name":"Fish N Chips","price":514,"category":"STARTERS","available":true},

{"name":"Margherita Pizza","price":239,"category":"PIZZAS","available":true,"desc":"Simple yet classic"},
{"name":"Fresh From The Garden Pizza","price":305,"category":"PIZZAS","available":true,"desc":"Mixed bell peppers, onion, tomato & olives"},
{"name":"Peri Peri Pizza","price":324,"category":"PIZZAS","available":true,"desc":"Tomato, roasted peppers, olives, spring onion & feta cheese"},
{"name":"Al Funghi Pizza","price":324,"category":"PIZZAS","available":true,"desc":"Mushroom, olives & jalapenos"},
{"name":"Chickenara Pizza","price":343,"category":"PIZZAS","available":true,"desc":"Chicken sausage, chicken salami, roast chicken & spring onion"},

{"name":"Vegetable Kebab Sizzler","price":458,"category":"SIZZLERS","available":true},
{"name":"Chicken Kebab Sizzler","price":600,"category":"SIZZLERS","available":true},
{"name":"Paneer Shashlik","price":458,"category":"SIZZLERS","available":true},
{"name":"Chicken Shashlik","price":572,"category":"SIZZLERS","available":true},

{"name":"Paneer Kathi Roll","price":210,"category":"KATHI ROLLS","available":true},
{"name":"Chicken Kathi Roll","price":229,"category":"KATHI ROLLS","available":true},

{"name":"Cream Of Tomato Soup","price":200,"category":"SOUPS","available":true},
{"name":"Chicken Clear Soup","price":200,"category":"SOUPS","available":true},
{"name":"Sweet Corn Vegetable Soup","price":200,"category":"SOUPS","available":true},
{"name":"Sweet Corn Chicken Soup","price":200,"category":"SOUPS","available":true},

{"name":"Fresh Garden Salad","price":124,"category":"SALADS","available":true},
{"name":"Sweet Corn & Sprouts Salad","price":200,"category":"SALADS","available":true},
{"name":"Aloo Chana Chaat Salad","price":238,"category":"SALADS","available":true},

{"name":"Mix Vegetable Raita","price":149,"category":"YOGURT","available":true},
{"name":"Boondi Raita","price":149,"category":"YOGURT","available":true},
{"name":"Pineapple Raita","price":159,"category":"YOGURT","available":true},
{"name":"Plain Curd","price":120,"category":"YOGURT","available":true},

{"name":"Sauteed Vegetable","price":320,"category":"WESTERN TREATS","available":true},
{"name":"Vegetable Au Gratin","price":330,"category":"WESTERN TREATS","available":true},
{"name":"Grilled Chicken Florentine","price":400,"category":"WESTERN TREATS","available":true},
{"name":"Chicken Stroganoff","price":400,"category":"WESTERN TREATS","available":true},

{"name":"Vegetable Pasta","price":305,"category":"PASTA","available":true},
{"name":"Chicken Pasta","price":324,"category":"PASTA","available":true},

{"name":"Steam Rice","price":162,"category":"RICE & BIRYANIS","available":true},
{"name":"Jeera Rice","price":181,"category":"RICE & BIRYANIS","available":true},
{"name":"Curd Rice","price":229,"category":"RICE & BIRYANIS","available":true},
{"name":"Dal Khichadi","price":286,"category":"RICE & BIRYANIS","available":true},
{"name":"Vegetable Biryani","price":353,"category":"RICE & BIRYANIS","available":true},
{"name":"Chicken Biryani","price":381,"category":"RICE & BIRYANIS","available":true},
{"name":"Mutton Biryani","price":620,"category":"RICE & BIRYANIS","available":true},

{"name":"Laccha Paratha","price":79,"category":"INDIAN BREADS","available":true},
{"name":"Pudina Paratha","price":79,"category":"INDIAN BREADS","available":true},
{"name":"Aloo Paratha","price":152,"category":"INDIAN BREADS","available":true},
{"name":"Paneer Paratha","price":200,"category":"INDIAN BREADS","available":true},
{"name":"Tandoori Roti","price":48,"category":"INDIAN BREADS","available":true},
{"name":"Butter Tandoori Roti","price":57,"category":"INDIAN BREADS","available":true},
{"name":"Butter Garlic Naan","price":114,"category":"INDIAN BREADS","available":true},
{"name":"Butter Naan","price":100,"category":"INDIAN BREADS","available":true},

{"name":"Gulab Jamun","price":114,"category":"DESSERTS & CAKES","available":true},
{"name":"Walnut Brownie","price":124,"category":"DESSERTS & CAKES","available":true},
{"name":"French Apple Tart","price":134,"category":"DESSERTS & CAKES","available":true},
{"name":"Blueberry Cheese Cake Slice","price":171,"category":"DESSERTS & CAKES","available":true},
{"name":"Mango Cheese Cake Slice","price":171,"category":"DESSERTS & CAKES","available":true},
{"name":"Chocolate Truffle Pastry","price":124,"category":"DESSERTS & CAKES","available":true},
{"name":"Chocolate Mousse","price":105,"category":"DESSERTS & CAKES","available":true},

{"name":"Jeera Aloo","price":219,"category":"INDIAN CURRIES","available":true,"desc":"Baby potatoes sauteed with cumin & herbs"},
{"name":"Paneer Makhani","price":343,"category":"INDIAN CURRIES","available":true,"desc":"Cottage cheese in creamy tomato gravy"},
{"name":"Paneer Tikka Butter Masala","price":353,"category":"INDIAN CURRIES","available":true,"desc":"Grilled cottage cheese in creamy tomato onion gravy"},
{"name":"Kadhai Murgh (4pc)","price":467,"category":"INDIAN CURRIES","available":true},
{"name":"Butter Chicken (2pc)","price":324,"category":"INDIAN CURRIES","available":true},
{"name":"Chicken Curry (4pc)","price":438,"category":"INDIAN CURRIES","available":true},
{"name":"Fish Curry","price":515,"category":"INDIAN CURRIES","available":true,"desc":"Mildly spiced tangy fish curry"}
]